<annotation>
	<folder>images</folder>
	<filename>0182.jpg</filename>
	<path>C:\Users\Admin\Documents\GitHub\Smart-Fridge\Data\Bounding images\Tomato\images\0182.jpg</path>
	<source>
		<database>Unknown</database>
	</source>
	<size>
		<width>228</width>
		<height>221</height>
		<depth>3</depth>
	</size>
	<segmented>0</segmented>
	<object>
		<name>tomato</name>
		<pose>Unspecified</pose>
		<truncated>0</truncated>
		<difficult>0</difficult>
		<bndbox>
			<xmin>2</xmin>
			<ymin>8</ymin>
			<xmax>222</xmax>
			<ymax>220</ymax>
		</bndbox>
	</object>
</annotation>
