<annotation>
	<folder>annotations</folder>
	<filename>2527.jpg</filename>
	<path>/content/Smart-Fridge/Data/Aug Images and Bounding 800x600/Beer/annotations/2527.xml</path>
	<source>
		<database>Unknown</database>
	</source>
	<size>
		<width>800</width>
		<height>600</height>
		<depth>3</depth>
	</size>
	<segmented>0</segmented>
	<object>
		<name>Beer</name>
		<pose>Unspecified</pose>
		<truncated>0</truncated>
		<difficult>0</difficult>
		<bndbox>
			<xmin>267</xmin>
			<ymin>-82</ymin>
			<xmax>773</xmax>
			<ymax>522</ymax>
		</bndbox>
	</object>
</annotation>
